setup.py
cz_wfcast.egg-info/PKG-INFO
cz_wfcast.egg-info/SOURCES.txt
cz_wfcast.egg-info/dependency_links.txt
cz_wfcast.egg-info/requires.txt
cz_wfcast.egg-info/top_level.txt
sunnyday/__init__.py
sunnyday/sunnyday.py